prawcore/__init__.py
prawcore/auth.py
prawcore/const.py
prawcore/exceptions.py
prawcore/rate_limit.py
prawcore/requestor.py
prawcore/sessions.py
prawcore/util.py
prawcore-3.0.1.dist-info/LICENSE.txt
prawcore-3.0.1.dist-info/WHEEL
prawcore-3.0.1.dist-info/METADATA
prawcore-3.0.1.dist-info/RECORD
