Metadata-Version: 2.3
Name: prawcore
Version: 3.0.1
Summary: Low-level communication layer for PRAW 4+.
Keywords: praw,reddit,api
Author-email: Bryce Boe <bbzbryce@gmail.com>
Maintainer-email: Bryce Boe <bbzbryce@gmail.com>
Requires-Python: ~=3.9
Classifier: Development Status :: 5 - Production/Stable
Classifier: Intended Audience :: Developers
Classifier: License :: OSI Approved :: BSD License
Classifier: Operating System :: OS Independent
Classifier: Natural Language :: English
Classifier: Programming Language :: Python
Classifier: Programming Language :: Python :: 3
Classifier: Programming Language :: Python :: 3.9
Classifier: Programming Language :: Python :: 3.10
Classifier: Programming Language :: Python :: 3.11
Classifier: Programming Language :: Python :: 3.12
Classifier: Programming Language :: Python :: 3.13
Requires-Dist: requests >=2.6.0, <3.0
Requires-Dist: coveralls ; extra == "ci"
Requires-Dist: packaging ; extra == "dev"
Requires-Dist: prawcore[lint] ; extra == "dev"
Requires-Dist: prawcore[test] ; extra == "dev"
Requires-Dist: pre-commit ; extra == "lint"
Requires-Dist: ruff ==0.9.* ; extra == "lint"
Requires-Dist: betamax >=0.8, <0.9 ; extra == "test"
Requires-Dist: pytest ==7.* ; extra == "test"
Requires-Dist: urllib3 ==1.* ; extra == "test"
Project-URL: Issue Tracker, https://github.com/praw-dev/prawcore/issues
Project-URL: Source Code, https://github.com/praw-dev/prawcore
Provides-Extra: ci
Provides-Extra: dev
Provides-Extra: lint
Provides-Extra: test
